{
  "courses": [
    {
      "id": 1,
      "name": "cai lùn mía",
      "decription": "kiến thức cơ bản"
    },
    {
      "name": "Thêm/sửa/xóa khóa học với Fetch và REST API",
      "decripstion": "Cập nhật tháng 7 năm 2022",
      "id": 2
    },
    {
      "namButton": "cai linf mai",
      "decriptionBut": "kieens thucs nang cao",
      "id": 3
    },
    {
      "namButton": "Vũ Minh Phương",
      "decriptionBut": "122121",
      "id": 4
    },
    {
      "namButton": "",
      "decriptionBut": "",
      "id": 5
    },
    {
      "namButton": "1",
      "decriptionBut": "2",
      "id": 6
    },
    {
      "namButton": {},
      "decriptionBut": {},
      "id": 7
    },
    {
      "namButton": {},
      "decriptionBut": {},
      "id": 8
    },
    {
      "namButton": {},
      "decriptionBut": {},
      "id": 9
    },
    {
      "namButton": {},
      "decriptionBut": {},
      "id": 10
    }
  ]
}